EasyROI/__init__.py
EasyROI/easyROI.py
EasyROI/utils.py
EasyROI-1.0.3.dist-info/LICENSE
EasyROI-1.0.3.dist-info/METADATA
EasyROI-1.0.3.dist-info/WHEEL
EasyROI-1.0.3.dist-info/top_level.txt
EasyROI-1.0.3.dist-info/RECORD
