Metadata-Version: 2.1
Name: EasyROI
Version: 1.0.3
Summary: ROI Helper
Home-page: https://github.com/saharshleo/easyROI
Author: Saharsh
License: MIT
Platform: UNKNOWN
Requires-Python: >=3.6
Requires-Dist: opencv-python (==4.5.1.48)
Requires-Dist: numpy (==1.19.5)
